spake2/__init__.py
spake2/_version.py
spake2/ed25519_basic.py
spake2/ed25519_group.py
spake2/groups.py
spake2/params.py
spake2/spake2.py
spake2/util.py
spake2/parameters/__init__.py
spake2/parameters/all.py
spake2/parameters/ed25519.py
spake2/parameters/i1024.py
spake2/parameters/i2048.py
spake2/parameters/i3072.py
spake2/test/__init__.py
spake2/test/common.py
spake2/test/myhkdf.py
spake2/test/test_compat.py
spake2/test/test_group.py
spake2/test/test_spake2.py
spake2/test/test_utils.py
spake2-0.9.dist-info/LICENSE
spake2-0.9.dist-info/METADATA
spake2-0.9.dist-info/WHEEL
spake2-0.9.dist-info/top_level.txt
spake2-0.9.dist-info/RECORD
